krakenclient/__init__.py
krakenclient/kraken_client_api.py
krakenclient-1.0.2.dist-info/LICENSE
krakenclient-1.0.2.dist-info/METADATA
krakenclient-1.0.2.dist-info/WHEEL
krakenclient-1.0.2.dist-info/top_level.txt
krakenclient-1.0.2.dist-info/RECORD
