Metadata-Version: 2.1
Name: krakenclient
Version: 1.0.2
Summary: A simple Kraken client API
Home-page: https://github.com/ApacheDatastreams/krakenclient
Author: Apache Datastreams
Author-email: admin@apachedatastreams.com
License: MIT
Platform: UNKNOWN
Classifier: Programming Language :: Python :: 3
Classifier: License :: OSI Approved :: MIT License
Classifier: Operating System :: OS Independent
Requires-Python: >=3
Requires-Dist: krakenex (==2.1.0)
